mixer/__init__.py
mixer/api.py
mixer/chat.py
mixer/constellation.py
mixer/exceptions.py
mixer/oauth.py
mixer/objects.py
mixer/utils.py
mixer/ws.py
mixer.py-0.0.3.dist-info/LICENSE
mixer.py-0.0.3.dist-info/METADATA
mixer.py-0.0.3.dist-info/WHEEL
mixer.py-0.0.3.dist-info/top_level.txt
mixer.py-0.0.3.dist-info/RECORD
