Metadata-Version: 2.1
Name: mixer.py
Version: 0.0.3
Summary: An unofficial Mixer API wrapper written in Python. 
Home-page: https://github.com/ooojustin/mixer.py
Author: Justin Garofolo
Author-email: justin@garofolo.net
License: UNKNOWN
Platform: UNKNOWN
Classifier: Programming Language :: Python :: 3
Classifier: License :: OSI Approved :: MIT License
Classifier: Operating System :: OS Independent
